raspunzel/__init__.py
raspunzel/run.py
raspunzel/utils.py
raspunzel/workspace.py
raspunzel-1.0.0.dist-info/entry_points.txt
raspunzel-1.0.0.dist-info/LICENSE
raspunzel-1.0.0.dist-info/WHEEL
raspunzel-1.0.0.dist-info/METADATA
raspunzel-1.0.0.dist-info/RECORD
